collective.vocabularies-1.0.5-py2.7-nspkg.pth
collective/vocabularies/__init__.py
collective/vocabularies/configure.zcml
collective/vocabularies/interfaces.py
collective/vocabularies/meta.zcml
collective/vocabularies/setuphandlers.py
collective/vocabularies/testing.py
collective/vocabularies/utils.py
collective/vocabularies/vocab.py
collective/vocabularies/browser/__init__.py
collective/vocabularies/browser/configure.zcml
collective/vocabularies/browser/overrides/.gitkeep
collective/vocabularies/browser/static/.gitkeep
collective/vocabularies/databases/countries.json
collective/vocabularies/locales/collective.vocabularies.pot
collective/vocabularies/locales/update.sh
collective/vocabularies/organisation/__init__.py
collective/vocabularies/organisation/configure.zcml
collective/vocabularies/organisation/factories.py
collective/vocabularies/organisation/vocab.py
collective/vocabularies/profiles/default/browserlayer.xml
collective/vocabularies/profiles/default/metadata.xml
collective/vocabularies/profiles/organisation/browserlayer.xml
collective/vocabularies/profiles/organisation/metadata.xml
collective/vocabularies/profiles/uninstall/browserlayer.xml
collective/vocabularies/technology/__init__.py
collective/vocabularies/technology/configure.zcml
collective/vocabularies/technology/interfaces.py
collective/vocabularies/technology/setuphandlers.py
collective/vocabularies/technology/testing.py
collective/vocabularies/technology/vocab.py
collective/vocabularies/technology/browser/__init__.py
collective/vocabularies/technology/browser/configure.zcml
collective/vocabularies/technology/browser/overrides/.gitkeep
collective/vocabularies/technology/browser/static/.gitkeep
collective/vocabularies/technology/databases/.gitkeep
collective/vocabularies/technology/databases/programming_languages.json
collective/vocabularies/technology/locales/collective.vocabularies.technology.pot
collective/vocabularies/technology/locales/update.sh
collective.vocabularies-1.0.5.dist-info/METADATA
collective.vocabularies-1.0.5.dist-info/WHEEL
collective.vocabularies-1.0.5.dist-info/entry_points.txt
collective.vocabularies-1.0.5.dist-info/namespace_packages.txt
collective.vocabularies-1.0.5.dist-info/top_level.txt
collective.vocabularies-1.0.5.dist-info/RECORD
